django_surveys-1.1.0.dist-info/METADATA
django_surveys-1.1.0.dist-info/RECORD
django_surveys-1.1.0.dist-info/WHEEL
django_surveys-1.1.0.dist-info/top_level.txt
surveys/__init__.py
surveys/admin.py
surveys/apps.py
surveys/constants.py
surveys/managers.py
surveys/models.py
surveys/serializers.py
surveys/settings.py
surveys/signals.py
surveys/urls.py
surveys/views.py
surveys/migrations/0001_squashed_0003_auto_20160803_1427.py
surveys/migrations/0002_auto_20161221_1120.py
surveys/migrations/0003_auto_20161223_1128.py
surveys/migrations/0004_auto_20161223_1129.py
surveys/migrations/0005_auto_20161223_1130.py
surveys/migrations/__init__.py
surveys/static/surveys/img/rating_star-o.png
surveys/templates/surveys/5-stars.html
surveys/templates/surveys/5-stars.txt
surveys/templates/surveys/survey-star-o.svg
surveys/templatetags/__init__.py
surveys/templatetags/surveys_tags.py
