Metadata-Version: 2.1
Name: django-surveys
Version: 1.1.0
Summary: A reusable Django app that lets users write feedback for any model
Home-page: https://github.com/founders4schools/django-surveys
Author: Founders4Schools
Author-email: dev@founders4schools.org.uk
License: MIT
Keywords: django-surveys
Platform: UNKNOWN
Classifier: Development Status :: 3 - Alpha
Classifier: Framework :: Django
Classifier: Framework :: Django :: 1.11
Classifier: Framework :: Django :: 2.0
Classifier: Intended Audience :: Developers
Classifier: License :: OSI Approved :: BSD License
Classifier: Natural Language :: English
Classifier: Programming Language :: Python :: 3
Classifier: Programming Language :: Python :: 3.5
Classifier: Programming Language :: Python :: 3.6
Requires-Dist: django
Requires-Dist: django-model-utils
Requires-Dist: djangorestframework (>=3.7)
Requires-Dist: django-braces (>=1.10.0)
